pyewjn/__init__.py
pyewjn/baskets.py
pyewjn/dielectric/__init__.py
pyewjn/dielectric/lindhard_dielectric.py
pyewjn/dielectric/low_k_nam.py
pyewjn/dielectric/nam_dielectric_coefficient_approximator.py
pyewjn/dielectric/sigma_nam.py
pyewjn/dielectric/sigma_nam_keep_gap.py
pyewjn/noise/__init__.py
pyewjn/noise/chi.py
pyewjn/noise/im_ref.py
pyewjn/noise/zeta.py
pyewjn/util/__init__.py
pyewjn/util/complex_integrate.py
pyewjn-0.3.0.dist-info/WHEEL
pyewjn-0.3.0.dist-info/METADATA
pyewjn-0.3.0.dist-info/RECORD
