Metadata-Version: 2.1
Name: pyewjn
Version: 0.3.0
Summary: 
Author: Deepak
Author-email: dmallubhotla+github@gmail.com
Requires-Python: >=3.8,<3.10
Classifier: Programming Language :: Python :: 3
Classifier: Programming Language :: Python :: 3.8
Classifier: Programming Language :: Python :: 3.9
Requires-Dist: numpy (>=1.21.1,<2.0.0)
Requires-Dist: scipy (>=1.8,<1.9)
